jupyterlab_blockly_ipylgbst/__init__.py
jupyterlab_blockly_ipylgbst/_version.py
jupyterlab_blockly_ipylgbst-0.1.1.data/data/share/jupyter/labextensions/jupyterlab-blockly-ipylgbst/package.json
jupyterlab_blockly_ipylgbst-0.1.1.data/data/share/jupyter/labextensions/jupyterlab-blockly-ipylgbst/static/156.a322e7f0ca93dec64485.js
jupyterlab_blockly_ipylgbst-0.1.1.data/data/share/jupyter/labextensions/jupyterlab-blockly-ipylgbst/static/156.a322e7f0ca93dec64485.js.map
jupyterlab_blockly_ipylgbst-0.1.1.data/data/share/jupyter/labextensions/jupyterlab-blockly-ipylgbst/static/194.28d050d2caa17305bd46.js
jupyterlab_blockly_ipylgbst-0.1.1.data/data/share/jupyter/labextensions/jupyterlab-blockly-ipylgbst/static/194.28d050d2caa17305bd46.js.map
jupyterlab_blockly_ipylgbst-0.1.1.data/data/share/jupyter/labextensions/jupyterlab-blockly-ipylgbst/static/222.b9b3d73fce50edc5152e.js
jupyterlab_blockly_ipylgbst-0.1.1.data/data/share/jupyter/labextensions/jupyterlab-blockly-ipylgbst/static/222.b9b3d73fce50edc5152e.js.map
jupyterlab_blockly_ipylgbst-0.1.1.data/data/share/jupyter/labextensions/jupyterlab-blockly-ipylgbst/static/250.76ce8fea5e55dd02bdab.js
jupyterlab_blockly_ipylgbst-0.1.1.data/data/share/jupyter/labextensions/jupyterlab-blockly-ipylgbst/static/250.76ce8fea5e55dd02bdab.js.map
jupyterlab_blockly_ipylgbst-0.1.1.data/data/share/jupyter/labextensions/jupyterlab-blockly-ipylgbst/static/287.599bd931084f4acc654a.js
jupyterlab_blockly_ipylgbst-0.1.1.data/data/share/jupyter/labextensions/jupyterlab-blockly-ipylgbst/static/287.599bd931084f4acc654a.js.map
jupyterlab_blockly_ipylgbst-0.1.1.data/data/share/jupyter/labextensions/jupyterlab-blockly-ipylgbst/static/310.20d48ac03275eb421b51.js
jupyterlab_blockly_ipylgbst-0.1.1.data/data/share/jupyter/labextensions/jupyterlab-blockly-ipylgbst/static/310.20d48ac03275eb421b51.js.map
jupyterlab_blockly_ipylgbst-0.1.1.data/data/share/jupyter/labextensions/jupyterlab-blockly-ipylgbst/static/318.a0628d485f755bf7e321.js
jupyterlab_blockly_ipylgbst-0.1.1.dist-info/METADATA
jupyterlab_blockly_ipylgbst-0.1.1.dist-info/WHEEL
jupyterlab_blockly_ipylgbst-0.1.1.dist-info/licenses/LICENSE
jupyterlab_blockly_ipylgbst-0.1.1.dist-info/RECORD
