Metadata-Version: 2.3
Name: jupyterlab_blockly_ipylgbst
Version: 0.1.1
Dynamic: Keywords
Summary: Blockly extension for JupyterLab to control the Lego Boost, using the ipylgbst library.
Project-URL: Homepage, https://github.com/jupyter-robotics/jupyterlab-blockly-ipylgbst
Project-URL: Bug Tracker, https://github.com/jupyter-robotics/jupyterlab-blockly-ipylgbst/issues
Project-URL: Repository, https://github.com/jupyter-robotics/jupyterlab-blockly-ipylgbst.git
Author-email: Denisa Checiu <denisa.checiu@quantstack.net>
License: BSD 3-Clause License
License-File: LICENSE
Classifier: Framework :: Jupyter
Classifier: Framework :: Jupyter :: JupyterLab
Classifier: Framework :: Jupyter :: JupyterLab :: 4
Classifier: Framework :: Jupyter :: JupyterLab :: Extensions
Classifier: Framework :: Jupyter :: JupyterLab :: Extensions :: Prebuilt
Classifier: License :: OSI Approved :: BSD License
Classifier: Programming Language :: Python
Classifier: Programming Language :: Python :: 3
Classifier: Programming Language :: Python :: 3.8
Classifier: Programming Language :: Python :: 3.9
Classifier: Programming Language :: Python :: 3.10
Classifier: Programming Language :: Python :: 3.11
Classifier: Programming Language :: Python :: 3.12
Requires-Python: >=3.8
Requires-Dist: ipylgbst<0.3,>=0.2.1
Requires-Dist: ipywidgets
Requires-Dist: jupyterlab-blockly<0.4,>=0.3.3
Requires-Dist: jupyterlab<5,>=4.0.0
Provides-Extra: dev
Requires-Dist: click; extra == 'dev'
Requires-Dist: jupyter-releaser; extra == 'dev'
